LICENSE
MANIFEST.in
README.md
setup.py
tap_appsflyer/__init__.py
tap_appsflyer.egg-info/PKG-INFO
tap_appsflyer.egg-info/SOURCES.txt
tap_appsflyer.egg-info/dependency_links.txt
tap_appsflyer.egg-info/entry_points.txt
tap_appsflyer.egg-info/requires.txt
tap_appsflyer.egg-info/top_level.txt
tap_appsflyer/schemas/raw_data/in_app_events.json
tap_appsflyer/schemas/raw_data/installations.json
tap_appsflyer/schemas/raw_data/organic_installs.json