Metadata-Version: 2.1
Name: tap-appsflyer
Version: 0.0.13
Summary: Singer.io tap for extracting data from the AppsFlyer API
Home-page: http://singer.io
Author: Stitch, Inc.
License: UNKNOWN
Platform: UNKNOWN
Classifier: Programming Language :: Python :: 3 :: Only
Provides-Extra: dev
License-File: LICENSE
